{
  "mode": "combat",
  "scenario_id": "normal_baseline",
  "dataset_version": "1.0.0",
  "seed": 1337,
  "monte_carlo_runs": 1,
  "wave_results": [
    {
      "wave": 1,
      "potential_damage": 11058.1241685024,
      "combat_damage": 9840.0,
      "effective_dps": 447.2727272727,
      "clear_time_s": 22.0,
      "leaks": 0.0,
      "enemy_hp_pool": 9840.0,
      "breakdown": {
        "Arrow Tower": 4920.0,
        "Frost Tower": 4920.0
      }
    },
    {
      "wave": 2,
      "potential_damage": 14893.903715832,
      "combat_damage": 14400.0,
      "effective_dps": 483.1522607397,
      "clear_time_s": 30.0,
      "leaks": 0.0,
      "enemy_hp_pool": 14400.0,
      "breakdown": {
        "Arrow Tower": 7247.2839110953,
        "Frost Tower": 7247.2839110953
      }
    }
  ],
  "totals": {
    "potential_damage": 25952.0278843344,
    "combat_damage": 24240.0,
    "leaks": 0.0,
    "economy": {
      "baseline_gold": 285.0,
      "baseline_essence": 42.0,
      "worker_gold_income": 168.0,
      "worker_essence_income": 18.0,
      "gross_gold_income": 453.0,
      "gross_essence_income": 60.0,
      "build_spend_gold": 92.0,
      "build_inflation_gold": 12.0,
      "build_actions": 1,
      "net_gold": 361.0,
      "net_essence": 60.0,
      "policy_id": "harvest",
      "workers": {
        "total": 4,
        "gold": 1,
        "essence": 3,
        "unassigned": 0
      }
    }
  }
}
